{"frames": {

"deco/deco0001.png":
{
	"frame": {"x":176,"y":426,"w":69,"h":99},
	"rotated": true,
	"trimmed": true,
	"spriteSourceSize": {"x":32,"y":37,"w":69,"h":99},
	"sourceSize": {"w":138,"h":147}
},
"deco/deco0002.png":
{
	"frame": {"x":705,"y":418,"w":72,"h":82},
	"rotated": true,
	"trimmed": true,
	"spriteSourceSize": {"x":33,"y":59,"w":72,"h":82},
	"sourceSize": {"w":138,"h":147}
},
"deco/deco0003.png":
{
	"frame": {"x":963,"y":387,"w":93,"h":142},
	"rotated": true,
	"trimmed": true,
	"spriteSourceSize": {"x":14,"y":0,"w":93,"h":142},
	"sourceSize": {"w":138,"h":147}
},
"deco/deco0004.png":
{
	"frame": {"x":823,"y":387,"w":138,"h":100},
	"rotated": false,
	"trimmed": true,
	"spriteSourceSize": {"x":0,"y":47,"w":138,"h":100},
	"sourceSize": {"w":138,"h":147}
},
"deco/deco0005.png":
{
	"frame": {"x":596,"y":418,"w":107,"h":73},
	"rotated": false,
	"trimmed": true,
	"spriteSourceSize": {"x":16,"y":73,"w":107,"h":73},
	"sourceSize": {"w":138,"h":147}
},
"grass-patches/grass-patches0001.png":
{
	"frame": {"x":1178,"y":354,"w":27,"h":27},
	"rotated": false,
	"trimmed": true,
	"spriteSourceSize": {"x":7,"y":6,"w":27,"h":27},
	"sourceSize": {"w":40,"h":33}
},
"grass-patches/grass-patches0002.png":
{
	"frame": {"x":1142,"y":249,"w":39,"h":32},
	"rotated": false,
	"trimmed": true,
	"spriteSourceSize": {"x":0,"y":1,"w":39,"h":32},
	"sourceSize": {"w":40,"h":33}
},
"grass-patches/grass-patches0003.png":
{
	"frame": {"x":1180,"y":322,"w":28,"h":30},
	"rotated": false,
	"trimmed": true,
	"spriteSourceSize": {"x":9,"y":3,"w":28,"h":30},
	"sourceSize": {"w":40,"h":33}
},
"grass-patches/grass-patches0004.png":
{
	"frame": {"x":789,"y":472,"w":24,"h":24},
	"rotated": false,
	"trimmed": true,
	"spriteSourceSize": {"x":9,"y":9,"w":24,"h":24},
	"sourceSize": {"w":40,"h":33}
},
"grass-patches/grass-patches0005.png":
{
	"frame": {"x":1107,"y":475,"w":21,"h":33},
	"rotated": true,
	"trimmed": true,
	"spriteSourceSize": {"x":13,"y":0,"w":21,"h":33},
	"sourceSize": {"w":40,"h":33}
},
"grass-patches/grass-patches0006.png":
{
	"frame": {"x":1142,"y":283,"w":36,"h":28},
	"rotated": false,
	"trimmed": true,
	"spriteSourceSize": {"x":4,"y":5,"w":36,"h":28},
	"sourceSize": {"w":40,"h":33}
},
"grass-patches/grass-patches0007.png":
{
	"frame": {"x":367,"y":426,"w":55,"h":37},
	"rotated": true,
	"trimmed": true,
	"spriteSourceSize": {"x":13,"y":12,"w":55,"h":37},
	"sourceSize": {"w":68,"h":49}
},
"pickups/pickup0001.png":
{
	"frame": {"x":1142,"y":181,"w":43,"h":32},
	"rotated": false,
	"trimmed": true,
	"spriteSourceSize": {"x":0,"y":0,"w":43,"h":32},
	"sourceSize": {"w":47,"h":36}
},
"pickups/pickup0002.png":
{
	"frame": {"x":1180,"y":285,"w":35,"h":28},
	"rotated": true,
	"trimmed": true,
	"spriteSourceSize": {"x":2,"y":2,"w":35,"h":28},
	"sourceSize": {"w":47,"h":36}
},
"pickups/pickup0003.png":
{
	"frame": {"x":1142,"y":313,"w":36,"h":26},
	"rotated": false,
	"trimmed": true,
	"spriteSourceSize": {"x":2,"y":4,"w":36,"h":26},
	"sourceSize": {"w":47,"h":36}
},
"pickups/pickup0004.png":
{
	"frame": {"x":784,"y":387,"w":37,"h":28},
	"rotated": false,
	"trimmed": true,
	"spriteSourceSize": {"x":0,"y":2,"w":37,"h":28},
	"sourceSize": {"w":47,"h":36}
},
"pickups/pickup0005.png":
{
	"frame": {"x":1142,"y":341,"w":34,"h":26},
	"rotated": false,
	"trimmed": true,
	"spriteSourceSize": {"x":2,"y":3,"w":34,"h":26},
	"sourceSize": {"w":47,"h":36}
},
"pine-1.png":
{
	"frame": {"x":784,"y":1,"w":177,"h":384},
	"rotated": false,
	"trimmed": false,
	"spriteSourceSize": {"x":0,"y":0,"w":177,"h":384},
	"sourceSize": {"w":177,"h":384}
},
"pine-2.png":
{
	"frame": {"x":963,"y":1,"w":177,"h":384},
	"rotated": false,
	"trimmed": false,
	"spriteSourceSize": {"x":0,"y":0,"w":177,"h":384},
	"sourceSize": {"w":177,"h":384}
},
"plants/plants0001.png":
{
	"frame": {"x":1142,"y":76,"w":31,"h":49},
	"rotated": true,
	"trimmed": true,
	"spriteSourceSize": {"x":26,"y":36,"w":31,"h":49},
	"sourceSize": {"w":65,"h":85}
},
"plants/plants0002.png":
{
	"frame": {"x":1107,"y":387,"w":38,"h":84},
	"rotated": true,
	"trimmed": true,
	"spriteSourceSize": {"x":27,"y":0,"w":38,"h":84},
	"sourceSize": {"w":65,"h":85}
},
"plants/plants0003.png":
{
	"frame": {"x":320,"y":426,"w":45,"h":67},
	"rotated": false,
	"trimmed": true,
	"spriteSourceSize": {"x":0,"y":18,"w":45,"h":67},
	"sourceSize": {"w":65,"h":85}
},
"plants/plants0004.png":
{
	"frame": {"x":98,"y":426,"w":38,"h":70},
	"rotated": false,
	"trimmed": true,
	"spriteSourceSize": {"x":15,"y":15,"w":38,"h":70},
	"sourceSize": {"w":65,"h":85}
},
"plants/plants0005.png":
{
	"frame": {"x":138,"y":426,"w":36,"h":70},
	"rotated": false,
	"trimmed": true,
	"spriteSourceSize": {"x":9,"y":15,"w":36,"h":70},
	"sourceSize": {"w":65,"h":85}
},
"plants/plants0006.png":
{
	"frame": {"x":277,"y":426,"w":41,"h":69},
	"rotated": false,
	"trimmed": true,
	"spriteSourceSize": {"x":15,"y":16,"w":41,"h":69},
	"sourceSize": {"w":65,"h":85}
},
"plants/plants0007.png":
{
	"frame": {"x":1142,"y":144,"w":45,"h":35},
	"rotated": false,
	"trimmed": true,
	"spriteSourceSize": {"x":15,"y":49,"w":45,"h":35},
	"sourceSize": {"w":65,"h":85}
},
"plants/plants0008.png":
{
	"frame": {"x":789,"y":417,"w":53,"h":32},
	"rotated": true,
	"trimmed": true,
	"spriteSourceSize": {"x":12,"y":53,"w":53,"h":32},
	"sourceSize": {"w":65,"h":85}
},
"plants/plants0009.png":
{
	"frame": {"x":1142,"y":1,"w":40,"h":54},
	"rotated": true,
	"trimmed": true,
	"spriteSourceSize": {"x":18,"y":29,"w":40,"h":54},
	"sourceSize": {"w":65,"h":85}
},
"plants/plants0010.png":
{
	"frame": {"x":50,"y":426,"w":46,"h":71},
	"rotated": false,
	"trimmed": true,
	"spriteSourceSize": {"x":15,"y":14,"w":46,"h":71},
	"sourceSize": {"w":65,"h":85}
},
"rocks/rocks0001.png":
{
	"frame": {"x":1183,"y":249,"w":34,"h":25},
	"rotated": true,
	"trimmed": true,
	"spriteSourceSize": {"x":22,"y":19,"w":34,"h":25},
	"sourceSize": {"w":83,"h":47}
},
"rocks/rocks0002.png":
{
	"frame": {"x":1107,"y":427,"w":83,"h":46},
	"rotated": false,
	"trimmed": true,
	"spriteSourceSize": {"x":0,"y":1,"w":83,"h":46},
	"sourceSize": {"w":83,"h":47}
},
"rocks/rocks0003.png":
{
	"frame": {"x":1142,"y":43,"w":51,"h":31},
	"rotated": false,
	"trimmed": true,
	"spriteSourceSize": {"x":17,"y":14,"w":51,"h":31},
	"sourceSize": {"w":83,"h":47}
},
"rocks/rocks0004.png":
{
	"frame": {"x":1142,"y":109,"w":46,"h":33},
	"rotated": false,
	"trimmed": true,
	"spriteSourceSize": {"x":20,"y":13,"w":46,"h":33},
	"sourceSize": {"w":83,"h":47}
},
"rocks/rocks0005.png":
{
	"frame": {"x":1142,"y":215,"w":41,"h":32},
	"rotated": false,
	"trimmed": true,
	"spriteSourceSize": {"x":21,"y":12,"w":41,"h":32},
	"sourceSize": {"w":83,"h":47}
},
"rocks/rocks0006.png":
{
	"frame": {"x":1,"y":426,"w":71,"h":47},
	"rotated": true,
	"trimmed": true,
	"spriteSourceSize": {"x":6,"y":0,"w":71,"h":47},
	"sourceSize": {"w":83,"h":47}
},
"tree-1.png":
{
	"frame": {"x":1,"y":1,"w":423,"h":368},
	"rotated": true,
	"trimmed": true,
	"spriteSourceSize": {"x":12,"y":0,"w":423,"h":368},
	"sourceSize": {"w":488,"h":368}
},
"tree-2.png":
{
	"frame": {"x":371,"y":1,"w":411,"h":415},
	"rotated": false,
	"trimmed": false,
	"spriteSourceSize": {"x":0,"y":0,"w":411,"h":415},
	"sourceSize": {"w":411,"h":415}
},
"trunks/trunks0001.png":
{
	"frame": {"x":503,"y":418,"w":91,"h":77},
	"rotated": false,
	"trimmed": true,
	"spriteSourceSize": {"x":5,"y":0,"w":91,"h":77},
	"sourceSize": {"w":96,"h":77}
},
"trunks/trunks0002.png":
{
	"frame": {"x":406,"y":418,"w":95,"h":77},
	"rotated": false,
	"trimmed": true,
	"spriteSourceSize": {"x":0,"y":0,"w":95,"h":77},
	"sourceSize": {"w":96,"h":77}
}},
"animations": {
	"deco/deco": ["deco/deco0001.png","deco/deco0002.png","deco/deco0003.png","deco/deco0004.png","deco/deco0005.png"],
	"grass-patches/grass-patches": ["grass-patches/grass-patches0001.png","grass-patches/grass-patches0002.png","grass-patches/grass-patches0003.png","grass-patches/grass-patches0004.png","grass-patches/grass-patches0005.png","grass-patches/grass-patches0006.png","grass-patches/grass-patches0007.png"],
	"pickups/pickup": ["pickups/pickup0001.png","pickups/pickup0002.png","pickups/pickup0003.png","pickups/pickup0004.png","pickups/pickup0005.png"],
	"pine": ["pine-1.png","pine-2.png"],
	"plants/plants": ["plants/plants0001.png","plants/plants0002.png","plants/plants0003.png","plants/plants0004.png","plants/plants0005.png","plants/plants0006.png","plants/plants0007.png","plants/plants0008.png","plants/plants0009.png","plants/plants0010.png"],
	"rocks/rocks": ["rocks/rocks0001.png","rocks/rocks0002.png","rocks/rocks0003.png","rocks/rocks0004.png","rocks/rocks0005.png","rocks/rocks0006.png"],
	"tree": ["tree-1.png","tree-2.png"],
	"trunks/trunks": ["trunks/trunks0001.png","trunks/trunks0002.png"]
},
"meta": {
	"app": "https://www.codeandweb.com/texturepacker",
	"version": "1.0",
	"image": "environment.png",
	"format": "RGBA8888",
	"size": {"w":1209,"h":498},
	"scale": "1",
	"smartupdate": "$TexturePacker:SmartUpdate:6d5f474b77c9238756e9fb6b1b095852:cc815e6d443e920a95e46457224d21f1:7abea815e3107eecbafa95ee71efdc50$"
}
}
